{
  "products": [
    {
      "id": 0,
      "img": "https://image.thehyundai.com/1/1/3/30/A2/hnm40A2303114_5.jpg",
      "title": "릴랙스드 오버셔츠",
      "price": 169000,
      "new": true,
      "size": [
        "M",
        "L"
      ],
      "desc": "이번 시즌 ARKET은 옷을 입는 본연의 즐거움을 다시 느낄 수 있는 아이템을 정성껏 만들었습니다.\n가먼트 워싱 처리한 오버셔츠로, 릴랙스 실루엣에 드로스트링 웨이스트와 스탠드 칼라, 패치 포켓이 특징입니다. \n편안함과 절제된 일상적 무드를 갖춘 디자인입니다."
    },
    {
      "id": 1,
      "img": "https://image.thehyundai.com/7/0/8/29/A2/hnm40A2298075_6.jpg",
      "title": "PINE 릴랙스드 배럴 진",
      "price": 169000,
      "new": true,
      "size": [
        "S",
        "M",
        "L"
      ],
      "desc": "PINE은 신축성이 없는 데님으로 만들어졌으며 미드 라이즈 웨이스트, 릴랙스드 핏, 그리고 배럴 레그가 특징입니다. \n 지퍼 플라이로 디자인되었습니다."
    },
    {
      "id": 2,
      "img": "https://image.thehyundai.com/1/9/1/30/A2/hnm40A2301916_6.jpg",
      "title": "릴랙스드 핏 포플린 셔츠",
      "price": 129000,
      "new": true,
      "size": [
        "32",
        "34",
        "42"
      ],
      "desc": "산뜻한 코튼 포플린 소재의 롱 슬리브 셔츠입니다. \n여유로우면서도 드레시한 실루엣의 버튼업 스타일입니다."
    },
    {
      "id": 3,
      "img": "https://image.thehyundai.com/4/3/9/28/A2/hnm40A2289345_image(58).jpg",
      "title": "스웨이드 파우치",
      "price": 229000,
      "new": true,
      "size": [
        "one"
      ],
      "desc": "깔끔한 라인과 심플한 형태가 특징인 가방으로, 시간이 지나도 편하게 사용하고 사랑받을 수 있도록 디자인된 가방입니다. \n부드러운 스웨이드 소재로 제작된 파우치로, 양쪽의 매듭 디테일의 드로스트링이 만들어내는 자연스러운 주름이 특징입니다. \n탈착 가능한 숄더 스트랩과 실용적인 내부 지퍼 포켓으로 편리하게 사용할 수 있습니다."
    },
    {
      "id": 4,
      "img": "https://image.thehyundai.com/0/0/5/28/A2/hnm40A2285004_5.jpg",
      "title": "시어서커 탑",
      "price": 119000,
      "new": false,
      "size": [
        "XS",
        "S",
        "M",
        "L"
      ]
    }
  ]
}
